LICENSE
MANIFEST.in
README.md
package.json
setup.py
rest_api_tester/__init__.py
rest_api_tester/py.typed
rest_api_tester/runner.py
rest_api_tester/test.py
rest_api_tester/utils.py
rest_api_tester.egg-info/PKG-INFO
rest_api_tester.egg-info/SOURCES.txt
rest_api_tester.egg-info/dependency_links.txt
rest_api_tester.egg-info/top_level.txt
rest_api_tester/client/__init__.py
rest_api_tester/client/base_client.py
rest_api_tester/client/response_data.py
rest_api_tester/parser/__init__.py
rest_api_tester/parser/base_parser.py
rest_api_tester/parser/json_parser.py