Metadata-Version: 2.1
Name: rest-api-tester
Version: 4.0.4
Summary: Rest API tester
Home-page: https://github.com/alexschimpf/python-rest-api-tester
Author: Alex Schimpf
Author-email: aschimpf1@gmail.com
Classifier: Programming Language :: Python :: 3.7
Classifier: Programming Language :: Python :: 3.8
Classifier: Programming Language :: Python :: 3.9
Classifier: Programming Language :: Python :: 3.10
Classifier: Programming Language :: Python :: 3.11
Requires-Python: >=3.7
License-File: LICENSE
